tinyvecdb-0.2.5.data/purelib/tinyvec/__init__.py
tinyvecdb-0.2.5.data/purelib/tinyvec/client.py
tinyvecdb-0.2.5.data/purelib/tinyvec/models.py
tinyvecdb-0.2.5.data/purelib/tinyvec/types.py
tinyvecdb-0.2.5.data/purelib/tinyvec/core/__init__.py
tinyvecdb-0.2.5.data/purelib/tinyvec/core/ctypes_bindings.py
tinyvecdb-0.2.5.data/purelib/tinyvec/core/tinyveclib.dll
tinyvecdb-0.2.5.data/purelib/tinyvec/core/utils.py
tinyvecdb-0.2.5.dist-info/METADATA
tinyvecdb-0.2.5.dist-info/WHEEL
tinyvecdb-0.2.5.dist-info/top_level.txt
tinyvecdb-0.2.5.dist-info/RECORD
