Metadata-Version: 2.4
Name: tinyvecdb
Version: 0.2.5
Summary: TinyVecDB is a high performance, lightweight, embedded vector database for similarity search.
Author: tylerpuig
License: MIT
Project-URL: Homepage, https://github.com/tylerpuig/tinyvec
Keywords: vector,database,similarity,search,vector database,tinyvec,vector search,similarity search
Classifier: Development Status :: 4 - Beta
Classifier: Intended Audience :: Developers
Classifier: License :: OSI Approved :: MIT License
Classifier: Programming Language :: Python :: 3
Classifier: Programming Language :: Python :: 3.9
Classifier: Programming Language :: Python :: 3.10
Classifier: Programming Language :: Python :: 3.11
Classifier: Programming Language :: Python :: 3.12
Classifier: Programming Language :: Python :: 3.13
Classifier: Topic :: Database
Classifier: Topic :: Scientific/Engineering :: Artificial Intelligence
Requires-Python: >=3.9
Requires-Dist: numpy>=1.20.0
Provides-Extra: dev
Requires-Dist: pytest>=8.3.4; extra == "dev"
Requires-Dist: pytest-asyncio>=0.25.3; extra == "dev"
Requires-Dist: setuptools>=75.8.0; extra == "dev"
Requires-Dist: wheel>=0.45.1; extra == "dev"
